setup.py
masonite_deploy.egg-info/PKG-INFO
masonite_deploy.egg-info/SOURCES.txt
masonite_deploy.egg-info/dependency_links.txt
masonite_deploy.egg-info/top_level.txt
masonite_heroku/commands/HerokuDBCommand.py
masonite_heroku/commands/HerokuDeployCommand.py
masonite_heroku/commands/HerokuEnvCommand.py
masonite_heroku/commands/HerokuMigrateCommand.py
masonite_heroku/commands/__init__.py
masonite_heroku/providers/DeployProvider.py
masonite_heroku/providers/__init__.py