Metadata-Version: 1.0
Name: masonite-deploy
Version: 0.0.1
Summary: Masonite deployment for Heroku
Home-page: https://github.com/MasoniteFramework/masonite
Author: Joseph Mancuso
Author-email: idmann509@gmail.com
License: UNKNOWN
Keywords: python web framework,python3,masonite
Platform: UNKNOWN
